disnake_compass/__init__.py
disnake_compass/api/__init__.py
disnake_compass/api/component.py
disnake_compass/api/parser.py
disnake_compass/fields.py
disnake_compass/impl/__init__.py
disnake_compass/impl/component/__init__.py
disnake_compass/impl/component/base.py
disnake_compass/impl/component/button.py
disnake_compass/impl/component/select.py
disnake_compass/impl/factory.py
disnake_compass/impl/manager.py
disnake_compass/impl/parser/__init__.py
disnake_compass/impl/parser/base.py
disnake_compass/impl/parser/builtins.py
disnake_compass/impl/parser/channel.py
disnake_compass/impl/parser/datetime.py
disnake_compass/impl/parser/emoji.py
disnake_compass/impl/parser/enum.py
disnake_compass/impl/parser/guild.py
disnake_compass/impl/parser/message.py
disnake_compass/impl/parser/snowflake.py
disnake_compass/impl/parser/user.py
disnake_compass/internal/__init__.py
disnake_compass/internal/di.py
disnake_compass/internal/omit.py
disnake_compass/py.typed
disnake_compass-1.0.1.dist-info/LICENSE
disnake_compass-1.0.1.dist-info/METADATA
disnake_compass-1.0.1.dist-info/WHEEL
disnake_compass-1.0.1.dist-info/entry_points.txt
disnake_compass-1.0.1.dist-info/RECORD
