Metadata-Version: 2.3
Name: disnake-compass
Version: 1.0.1
Summary: An extension for disnake aimed at making component interactions with listeners somewhat less cumbersome.
License: MIT
Author: Chromosomologist
Author-email: chromosomologist@gmail.com
Requires-Python: >=3.10,<4.0
Classifier: License :: OSI Approved :: MIT License
Classifier: Programming Language :: Python :: 3
Classifier: Programming Language :: Python :: 3.10
Classifier: Programming Language :: Python :: 3.11
Classifier: Programming Language :: Python :: 3.12
Classifier: Programming Language :: Python :: 3.13
Requires-Dist: attrs (>=24.3)
Requires-Dist: disnake (>=2.10,<3.0)
Requires-Dist: typing-extensions (>=4.10.0,<5.0.0)
